codexec/main.py
codexec-0.1.10.dist-info/LICENSE
codexec-0.1.10.dist-info/METADATA
codexec-0.1.10.dist-info/WHEEL
codexec-0.1.10.dist-info/entry_points.txt
codexec-0.1.10.dist-info/top_level.txt
codexec-0.1.10.dist-info/RECORD
