Metadata-Version: 2.1
Name: codexec
Version: 0.1.10
Summary: compiles and executes code files written in c, cpp, java, python and javascript
Author-email: prajesh <prajesh.eleven118@gmail.com>
Maintainer-email: prajesh <prajesh.eleven118@gmail.com>
License: MIT License
Project-URL: bugs, https://github.com/pr4j3sh/codexec/issues
Project-URL: homepage, https://github.com/pr4j3sh/codexec
License-File: LICENSE
Requires-Dist: requests
